streamnai
