Metadata-Version: 2.1
Name: streamn
Version: 1.0.2
Summary: a python library to use Streamn API's 
Home-page: UNKNOWN
Author: B. sai reddy Developer
Author-email: sai@streamn.com
License: UNKNOWN
Project-URL: Bug Reports, https://github.com/saireddy12/streamn_sdk/issues
Project-URL: Source, https://github.com/saireddy12/streamn_sdk
Keywords: streamn,ASR,ASR API,Speech Recognition API,Audio Labs
Platform: UNKNOWN
Classifier: Development Status :: 3 - Alpha
Classifier: Intended Audience :: Developers
Classifier: Topic :: Software Development :: Build Tools
Classifier: License :: OSI Approved :: MIT License
Classifier: Programming Language :: Python :: 3
Classifier: Programming Language :: Python :: 3.7
Classifier: Programming Language :: Python :: 3.8
Classifier: Programming Language :: Python :: 3.9
Classifier: Programming Language :: Python :: 3.10
Classifier: Programming Language :: Python :: 3 :: Only
Requires-Python: >=3.7
